byted_overpass_scbp_ls_risk_ticket/__init__.py
byted_overpass_scbp_ls_risk_ticket-0.0.1.dist-info/METADATA
byted_overpass_scbp_ls_risk_ticket-0.0.1.dist-info/WHEEL
byted_overpass_scbp_ls_risk_ticket-0.0.1.dist-info/top_level.txt
byted_overpass_scbp_ls_risk_ticket-0.0.1.dist-info/RECORD
